cellregmap/__init__.py
cellregmap/_cellregmap.py
cellregmap/_math.py
cellregmap/_simulate.py
cellregmap/_types.py
cellregmap/test/__init__.py
cellregmap/test/old_test_struct_lmm2.py
cellregmap/test/test_fixed_gxe.py
cellregmap/test/test_math.py
cellregmap/test/test_simulation.py
cellregmap/test/test_struct_lmm2.py
cellregmap-0.0.3.dist-info/LICENSE
cellregmap-0.0.3.dist-info/METADATA
cellregmap-0.0.3.dist-info/WHEEL
cellregmap-0.0.3.dist-info/top_level.txt
cellregmap-0.0.3.dist-info/zip-safe
cellregmap-0.0.3.dist-info/RECORD
