Metadata-Version: 2.1
Name: cellregmap
Version: 0.0.3
Summary: A linear mixed model framework to map multivariate context-specific eQTL using single-cell RNA-seq data.
Home-page: https://github.com/limix/CellRegMap
Author: Anna Cuomo, Danilo Horta
Author-email: acuomo@ebi.ac.uk
Maintainer: Danilo Horta
Maintainer-email: horta@ebi.ac.uk
License: MIT
Download-URL: https://github.com/limix/CellRegMap
Keywords: scRNA-seq,eQTL,context-specific regulation
Platform: Windows
Platform: MacOS
Platform: Linux
Classifier: Development Status :: 5 - Production/Stable
Classifier: License :: OSI Approved :: MIT License
Classifier: Operating System :: OS Independent
Classifier: Programming Language :: Python
Requires-Python: >=3.6
Requires-Dist: chiscore (>=0.2.3)
Requires-Dist: glimix-core (>=3.1.12)
Requires-Dist: numpy-sugar (>=1.5.1)
Requires-Dist: numpy (>=1.17.5)
Requires-Dist: pytest (>=5.4.3)
Requires-Dist: scipy (>=1.2.3)
Requires-Dist: tqdm (>=4.41.1)
